basisopt/#parallelise.py#
basisopt/TODO.txt
basisopt/__init__.py
basisopt/api.py
basisopt/basis/.DS_Store
basisopt/basis/TODO.txt
basisopt/basis/__init__.py
basisopt/basis/atomic.py
basisopt/basis/basis.py
basisopt/basis/guesses.py
basisopt/basis/jkfit.py
basisopt/basis/molecular.py
basisopt/basis/zetatools.py
basisopt/bse_wrapper.py
basisopt/containers.py
basisopt/data.py
basisopt/exceptions.py
basisopt/molecule.py
basisopt/opt/TODO.txt
basisopt/opt/__init__.py
basisopt/opt/eventemper.py
basisopt/opt/optimizers.py
basisopt/opt/preconditioners.py
basisopt/opt/reduce.py
basisopt/opt/regularisers.py
basisopt/opt/strategies.py
basisopt/optrecord.py
basisopt/parallelise.py
basisopt/testing/TODO.txt
basisopt/testing/__init__.py
basisopt/testing/dunham.py
basisopt/testing/rank.py
basisopt/testing/test.py
basisopt/util.py
basisopt/viz/TODO.txt
basisopt/viz/basis.py
basisopt/viz/orbital.py
basisopt/wrappers/.DS_Store
basisopt/wrappers/TODO.txt
basisopt/wrappers/__init__.py
basisopt/wrappers/dummy.py
basisopt/wrappers/molpro.py
basisopt/wrappers/orca.py
basisopt/wrappers/psi4.py
basisopt/wrappers/wrapper.py
basisopt-1.0.1.dist-info/LICENSE
basisopt-1.0.1.dist-info/METADATA
basisopt-1.0.1.dist-info/WHEEL
basisopt-1.0.1.dist-info/RECORD
