Metadata-Version: 2.1
Name: basisopt
Version: 1.0.1
Summary: Automatic basis set optimization for quantum chemistry
License: MIT
Author: Robert Shaw
Author-email: robertshaw383@gmail.com
Requires-Python: >=3.9,<3.12
Classifier: License :: OSI Approved :: MIT License
Classifier: Programming Language :: Python :: 3
Classifier: Programming Language :: Python :: 3.9
Classifier: Programming Language :: Python :: 3.10
Classifier: Programming Language :: Python :: 3.11
Requires-Dist: basis-set-exchange (>=0.9,<0.10)
Requires-Dist: colorlog (>=6.7.0,<7.0.0)
Requires-Dist: matplotlib (>=3.7.1,<4.0.0)
Requires-Dist: mendeleev (==0.9)
Requires-Dist: monty (>=2022.9.9,<2023.0.0)
Requires-Dist: numpy (>=1.24.2,<2.0.0)
Requires-Dist: pandas (>=1.5.3,<2.0.0)
Requires-Dist: scipy (>=1.10.1,<2.0.0)
